vaccbot/__init__.py
vaccbot-0.1.0.dist-info/METADATA
vaccbot-0.1.0.dist-info/WHEEL
vaccbot-0.1.0.dist-info/RECORD
